autosell_rmq/__init__.py
autosell_rmq/consumer.py
autosell_rmq/producer.py
autosell_rmq-0.1.3.dist-info/METADATA
autosell_rmq-0.1.3.dist-info/WHEEL
autosell_rmq-0.1.3.dist-info/RECORD
