Metadata-Version: 2.3
Name: autosell-rmq
Version: 0.1.3
Summary: 
Author: Zhanibek
Author-email: rzhanik@gmail.com
Requires-Python: >=3.11,<4.0.0
Classifier: Programming Language :: Python :: 3
Classifier: Programming Language :: Python :: 3.11
Classifier: Programming Language :: Python :: 3.12
Classifier: Programming Language :: Python :: 3.13
Requires-Dist: aio-pika (>=9.5.5,<10.0.0)
